pyremotedata/__init__.py
pyremotedata/config.py
pyremotedata/dataloader.py
pyremotedata/implicit_mount.py
pyremotedata-0.1.6.dist-info/METADATA
pyremotedata-0.1.6.dist-info/WHEEL
pyremotedata-0.1.6.dist-info/licenses/LICENSE
pyremotedata-0.1.6.dist-info/RECORD
