Metadata-Version: 2.4
Name: pyremotedata
Version: 0.1.6
Summary: A package for low- and high-level high-bandwidth asynchronous data transfer
Project-URL: Homepage, https://github.com/asgersvenning/pyremotedata
Project-URL: Bug Tracker, https://github.com/asgersvenning/pyremotedata/issues
Author-email: Asger Svenning <asgersvenning@gmail.com>
License-File: LICENSE
Classifier: License :: OSI Approved :: MIT License
Classifier: Operating System :: OS Independent
Classifier: Programming Language :: Python :: 3
Requires-Python: >=3.10
Requires-Dist: pyyaml>=6.0.1
Requires-Dist: tqdm>=4.67.1
Provides-Extra: full
Requires-Dist: colorlog>=6.9.0; extra == 'full'
Requires-Dist: torch>=2.0.1; extra == 'full'
Requires-Dist: torchvision>=0.15.2; extra == 'full'
Requires-Dist: wrapt-timeout-decorator>=1.5.1; extra == 'full'
